LICENSE
README.md
setup.cfg
setup.py
abacusai/__init__.py
abacusai/abacus_api.py
abacusai/address.py
abacusai/agent.py
abacusai/agent_chat_message.py
abacusai/agent_conversation.py
abacusai/agent_data_document_info.py
abacusai/agent_data_execution_result.py
abacusai/agent_version.py
abacusai/ai_building_task.py
abacusai/algorithm.py
abacusai/annotation.py
abacusai/annotation_config.py
abacusai/annotation_document.py
abacusai/annotation_entry.py
abacusai/annotations_status.py
abacusai/api_client_utils.py
abacusai/api_endpoint.py
abacusai/api_key.py
abacusai/app_user_group.py
abacusai/app_user_group_sign_in_token.py
abacusai/application_connector.py
abacusai/audio_gen_settings.py
abacusai/audio_url_result.py
abacusai/audit_log.py
abacusai/batch_prediction.py
abacusai/batch_prediction_version.py
abacusai/batch_prediction_version_logs.py
abacusai/bot_info.py
abacusai/categorical_range_violation.py
abacusai/chat_message.py
abacusai/chat_session.py
abacusai/chatllm_computer.py
abacusai/chatllm_computer_status.py
abacusai/chatllm_memory.py
abacusai/chatllm_project.py
abacusai/chatllm_project_permissions.py
abacusai/chatllm_referral_invite.py
abacusai/chatllm_task.py
abacusai/client.py
abacusai/code_agent_response.py
abacusai/code_autocomplete_edit_prediction_response.py
abacusai/code_autocomplete_response.py
abacusai/code_bot.py
abacusai/code_edit.py
abacusai/code_edit_response.py
abacusai/code_edits.py
abacusai/code_embeddings.py
abacusai/code_llm_changed_files.py
abacusai/code_source.py
abacusai/code_suggestion_validation_response.py
abacusai/code_summary_response.py
abacusai/codellm_embedding_constants.py
abacusai/compute_point_info.py
abacusai/concatenation_config.py
abacusai/constants_autocomplete_response.py
abacusai/cpu_gpu_memory_specs.py
abacusai/cryptography.py
abacusai/custom_chat_instructions.py
abacusai/custom_domain.py
abacusai/custom_loss_function.py
abacusai/custom_metric.py
abacusai/custom_metric_version.py
abacusai/custom_train_function_info.py
abacusai.egg-info/PKG-INFO
abacusai.egg-info/SOURCES.txt
abacusai.egg-info/dependency_links.txt
abacusai.egg-info/requires.txt
abacusai.egg-info/top_level.txt
abacusai.egg-info/zip-safe
