Metadata-Version: 2.1
Name: abacusai
Version: 1.4.76
Summary: Abacus.AI Python Client Library
Home-page: https://github.com/abacusai/api-python
Author: Abacus.AI
Author-email: dev@abacus.ai
License: MIT
Classifier: Development Status :: 5 - Production/Stable
Classifier: Intended Audience :: Developers
Classifier: Topic :: Utilities
Classifier: Programming Language :: Python :: 3
Classifier: Programming Language :: Python :: 3.8
Classifier: Programming Language :: Python :: 3.9
Classifier: Programming Language :: Python :: 3.10
Classifier: Programming Language :: Python :: 3.11
Classifier: Programming Language :: Python :: 3.12
License-File: LICENSE
